verysimplemodule/__init__.py
verysimplemodule/add.py
verysimplemodule/subtract.py
verysimplemodule/extras/__init__.py
verysimplemodule/extras/divide.py
verysimplemodule/extras/multiply.py
verysimplemodule1102-0.0.1.dist-info/METADATA
verysimplemodule1102-0.0.1.dist-info/WHEEL
verysimplemodule1102-0.0.1.dist-info/top_level.txt
verysimplemodule1102-0.0.1.dist-info/RECORD
